odin/__init__.py
odin/model/__init__.py
odin/model/baseline.py
odin/timeseries/__init__.py
odin/timeseries/forecast_window.py
odin_pkg_rioatmadja2018-0.1.1685316459.dist-info/METADATA
odin_pkg_rioatmadja2018-0.1.1685316459.dist-info/WHEEL
odin_pkg_rioatmadja2018-0.1.1685316459.dist-info/top_level.txt
odin_pkg_rioatmadja2018-0.1.1685316459.dist-info/zip-safe
odin_pkg_rioatmadja2018-0.1.1685316459.dist-info/RECORD
