Metadata-Version: 2.1
Name: odin-pkg-rioatmadja2018
Version: 0.1.1685316459
Summary: Python wheel Keras wrapper for forecasting timeseries
Author: Rio Atmadja
Author-email: rioatmadja2018@gmail.com
Classifier: Programming Language :: Python :: 3
Classifier: Operating System :: OS Independent
Classifier: Intended Audience :: Developers
Requires-Python: >=3.8
Requires-Dist: pandas
Requires-Dist: squarify
Requires-Dist: tensorflow
Requires-Dist: numpy
Requires-Dist: seaborn
Requires-Dist: statsmodels
